py_releases-0.1.0.data/data/releases_infos/infos.json
python_releases/__init__.py
python_releases/infos.py
python_releases/releases.py
python_releases/scrapper.py
python_releases/releases_infos/infos.json
py_releases-0.1.0.dist-info/LICENSE
py_releases-0.1.0.dist-info/METADATA
py_releases-0.1.0.dist-info/WHEEL
py_releases-0.1.0.dist-info/top_level.txt
py_releases-0.1.0.dist-info/RECORD
