Metadata-Version: 2.1
Name: py-releases
Version: 0.1.0
Summary: A package that get the avaliable python versions
Home-page: https://github.com/kuticoski/py-releases
Author: Gr Kuticoski
License: GPL-2.0
Platform: UNKNOWN
Classifier: Intended Audience :: Developers
Classifier: Programming Language :: Python :: 3
Classifier: Programming Language :: Python :: 3.9
Classifier: Operating System :: POSIX :: Linux
Requires-Dist: beautifulsoup4 (==4.9.3)
Requires-Dist: requests (==2.26.0)
